Metadata-Version: 2.1
Name: demo-sna
Version: 0.4.0
Summary: Python Boilerplate contains all the boilerplate you need to create a Python package.
Home-page: https://github.com/eng-aomar/demo
Author: Alaa' Omar
Author-email: alaa.omer2009@gmail.com
License: MIT license
Keywords: demo_sna
Requires-Python: >=3.7.0, <3.11
License-File: LICENSE
License-File: AUTHORS.rst
Requires-Dist: six (==1.16.0)
Requires-Dist: farasapy (==0.0.14)
Requires-Dist: tqdm (==4.62.2)
Requires-Dist: requests (==2.25.1)
Requires-Dist: regex (==2021.4.4)
